graphviz_code_viewer/__init__.py
graphviz_code_viewer/about.py
graphviz_code_viewer/desktop.py
graphviz_code_viewer/program.old.py
graphviz_code_viewer/program.py
graphviz_code_viewer/icons/logo.png
graphviz_code_viewer/modules/__init__.py
graphviz_code_viewer/modules/configure.py
graphviz_code_viewer/modules/wabout.py
graphviz_code_viewer-0.1.0.dist-info/licenses/LICENSE
graphviz_code_viewer-0.1.0.dist-info/METADATA
graphviz_code_viewer-0.1.0.dist-info/WHEEL
graphviz_code_viewer-0.1.0.dist-info/entry_points.txt
graphviz_code_viewer-0.1.0.dist-info/top_level.txt
graphviz_code_viewer-0.1.0.dist-info/RECORD
